htmpl_template/__init__.py
htmpl_template/__main__.py
htmpl_template/cli.py
htmpl_template-0.0.1.dist-info/METADATA
htmpl_template-0.0.1.dist-info/WHEEL
htmpl_template-0.0.1.dist-info/entry_points.txt
htmpl_template-0.0.1.dist-info/licenses/LICENSE
htmpl_template-0.0.1.dist-info/RECORD
