Metadata-Version: 2.4
Name: htmpl-template
Version: 0.0.1
Summary: Starter template for projects using 'htmpl'
Project-URL: Homepage, https://github.com/rmyers/htmpl-template
Project-URL: Documentation, https://github.com/rmyers/htmpl-template#readme
Project-URL: Repository, https://github.com/rmyers/htmpl-template
Author-email: Robert Myers <robert@julython.org>
License-Expression: MIT
License-File: LICENSE
Keywords: fastapi,html,htmx,pico,t-strings,templating
Classifier: Development Status :: 3 - Alpha
Classifier: Framework :: FastAPI
Classifier: Intended Audience :: Developers
Classifier: Programming Language :: Python :: 3.14
Classifier: Topic :: Internet :: WWW/HTTP :: Dynamic Content
Classifier: Topic :: Text Processing :: Markup :: HTML
Classifier: Typing :: Typed
Requires-Python: >=3.14
Requires-Dist: copier
Provides-Extra: dev
Requires-Dist: cuneus; extra == 'dev'
Requires-Dist: fastapi; extra == 'dev'
Requires-Dist: htmpl; extra == 'dev'
Requires-Dist: mistune; extra == 'dev'
Requires-Dist: pytest-asyncio>=1.3.0; extra == 'dev'
Requires-Dist: pytest-cov>=7.0.0; extra == 'dev'
Requires-Dist: pytest-mock>=3.15.1; extra == 'dev'
Requires-Dist: pytest>=9.0.2; extra == 'dev'
Requires-Dist: python-multipart; extra == 'dev'
Requires-Dist: rdflib; extra == 'dev'
Requires-Dist: tdom; extra == 'dev'
